final-project/hw/model.svh
// Auto-generated model memory
localparam logic [31:0] MODEL_MEM [0:565] = '{
    32'h9964d36b,
    32'hb0ce52d0,
    32'h4fc275f2,
    32'h59129273,
    32'hd6cbc705,
    32'h6424e95b,
    32'h442608ce,
    32'hddba850b,
    32'h26ee1ae5,
    32'hbfd85b5d,
    32'h3a381588,
    32'hadbc2601,
    32'h8e50cb11,
    32'h615700c7,
    32'hdb4c1c19,
    32'hb6a976f2,
    32'h6854adcb,
    32'h1908799c,
    32'h72ba4196,
    32'hf76c7f48,
    32'h265469fb,
    32'h29e3011d,
    32'haa3f3caa,
    32'h3ecea7ce,
    32'h38de8b1f,
    32'had0a49a1,
    32'hb38c418e,
    32'ha742c179,
    32'h3d84981d,
    32'hc67558cc,
    32'hb1d1ca9b,
    32'h8a614e74,
    32'h4a5d76ba,
    32'h8b656567,
    32'h919881fc,
    32'h2af1a4a2,
    32'h58fd9d85,
    32'hbf0eb14c,
    32'ha3af695e,
    32'h6f53d0e0,
    32'h39d9ade0,
    32'hb7410dec,
    32'hf1892b3e,
    32'had613431,
    32'h398537cd,
    32'hac027145,
    32'h928f150e,
    32'hb4d44afd,
    32'h5ec48a43,
    32'h22d7d853,
    32'h63348544,
    32'hb3842642,
    32'hb243015b,
    32'h03f40496,
    32'hfb4d9f10,
    32'hea1138f4,
    32'h0115916d,
    32'hc20f90ca,
    32'he0382116,
    32'h7973f261,
    32'hfbebf9bf,
    32'h837c46b6,
    32'h7d4e6b15,
    32'hfb0828f5,
    32'h6c31fe42,
    32'h3750a1de,
    32'hbb2991a0,
    32'h31a81695,
    32'h0273f5e2,
    32'h8d6f0090,
    32'h3a24ae01,
    32'he0983bf9,
    32'h27af2580,
    32'had58663c,
    32'h3d4a96c9,
    32'he886088c,
    32'hb6eb6b2e,
    32'hf1cd86b0,
    32'h7f64be41,
    32'h783761d7,
    32'h8005e266,
    32'h50bf8a95,
    32'h6fe0ac7d,
    32'h6919fe6f,
    32'hd1adb9f0,
    32'h4774a6d4,
    32'hbfc0ab84,
    32'h83316c71,
    32'h9128d61a,
    32'h4277d6d6,
    32'heb314f54,
    32'h4e387af7,
    32'hc2853520,
    32'h35092e96,
    32'hb27be372,
    32'h8aa2f674,
    32'hae958010,
    32'h52d7d6b9,
    32'h369779b0,
    32'h60cbb85a,
    32'h71de7d98,
    32'hb75abfe9,
    32'ha0a97394,
    32'h9cec8cbd,
    32'h36af2f9c,
    32'hd8c8efa1,
    32'h9e4e9ac9,
    32'h80866dbd,
    32'hb6e77abc,
    32'h07dd249c,
    32'hbd6dfb89,
    32'h384d2fdd,
    32'h3577fb2e,
    32'h0d090bbd,
    32'h3d5d7aa2,
    32'hb84b82b9,
    32'ha1239694,
    32'hec5a435e,
    32'h8f00ef09,
    32'h9a6348bb,
    32'h06af1612,
    32'hf870ef41,
    32'h8e81caf6,
    32'h0df1443f,
    32'h6f1c2de5,
    32'hd556be3a,
    32'heef5ba50,
    32'h66d6345c,
    32'h71eb53d8,
    32'h965a30d0,
    32'he90a50e0,
    32'hb479179b,
    32'hc2ab145e,
    32'h61d06808,
    32'h4c4151da,
    32'h6579cf65,
    32'hf61b63bc,
    32'h3ba06d69,
    32'h300790b5,
    32'hb7ebc989,
    32'h21a39270,
    32'h8578d4fc,
    32'hfdf74e3e,
    32'hca676fb0,
    32'h5d497226,
    32'h11b292fb,
    32'h48f738b5,
    32'h61d9b74e,
    32'hfe8dc91e,
    32'h508b6ca1,
    32'h0c8a58f7,
    32'h094b456f,
    32'hb79b0f1b,
    32'h7088f1a1,
    32'h44d4dbd2,
    32'h11abec3d,
    32'h93771e09,
    32'h9b22590c,
    32'h6ab104d1,
    32'h556af0f1,
    32'h315711a2,
    32'hd767b244,
    32'h1afe16d8,
    32'hbba5cd91,
    32'h412db542,
    32'hee0ef3a4,
    32'h0eb9a836,
    32'h8371dc23,
    32'h403b50b5,
    32'hf2d21e5a,
    32'hca5b5e5d,
    32'hc2ac1aa4,
    32'h053b5657,
    32'ha8f2af47,
    32'h2b69fef4,
    32'h41b513a6,
    32'ha7e76a16,
    32'hd9b07f09,
    32'h0deadce5,
    32'h05bd9fa5,
    32'h5daeabfd,
    32'h13a855cb,
    32'hd8efd695,
    32'hc56cff58,
    32'hfc9e91cb,
    32'h75887582,
    32'hc01631d4,
    32'h156ed3cd,
    32'hdb86bad1,
    32'h394fd2b6,
    32'h8d2fee22,
    32'h14a80431,
    32'h4e5ae434,
    32'h08479e7d,
    32'hec19354b,
    32'h7a788d4e,
    32'h850f7742,
    32'h9cbaf8c1,
    32'habab28bc,
    32'he9c9fc2a,
    32'hbbb9c55a,
    32'h96330606,
    32'hd94bd6b1,
    32'h4e76dff4,
    32'h2e50d694,
    32'h7ad65b09,
    32'h02fac57a,
    32'h1abbc106,
    32'h8ff2f601,
    32'h7f5dcdf3,
    32'hee0024d3,
    32'h7e9a52ff,
    32'he8b375e0,
    32'haf57da26,
    32'hf617203b,
    32'h66dc9a24,
    32'h3d5a9e02,
    32'h9dd744b2,
    32'he2cf403a,
    32'h5246bfb8,
    32'ha74266b6,
    32'hd8538e71,
    32'h3761b6d0,
    32'h42850767,
    32'h5feea204,
    32'hc0771d44,
    32'hb11d526a,
    32'he340e134,
    32'ha864f0de,
    32'hd200aced,
    32'h7c8e3ada,
    32'h978bb949,
    32'h6895ed19,
    32'h8c0b3987,
    32'ha20e241e,
    32'hb0999c08,
    32'h1a83a9cc,
    32'h2f2ca6c6,
    32'hb02ebd81,
    32'h664603c8,
    32'h4b3855e4,
    32'h6e75a6be,
    32'ha70bac5d,
    32'h2010b3c5,
    32'hcb107031,
    32'h92558f82,
    32'he2443e3a,
    32'h6cdb1b82,
    32'hab82ea60,
    32'h4ef78ac7,
    32'hef30a958,
    32'h6a7ae703,
    32'hc740fe16,
    32'h62f78a27,
    32'h6f64bc69,
    32'h7a5453a6,
    32'h00000000,
    32'h00000000,
    32'h00000000,
    32'h00000000,
    32'h00000000,
    32'h00000000,
    32'h00000000,
    32'h00000000,
    32'h00000000,
    32'h00000000,
    32'h00000000,
    32'h00000000,
    32'h00000000,
    32'h00000000,
    32'h00000000,
    32'h00000000,
    32'h00000000,
    32'h00000000,
    32'h00000000,
    32'h00000000,
    32'h00000000,
    32'h00000000,
    32'h00000000,
    32'h00000000,
    32'h00000000,
    32'h00000000,
    32'h00000000,
    32'h00000000,
    32'h00000000,
    32'h00000000,
    32'h00000000,
    32'h00000000,
    32'h00000000,
    32'h00000000,
    32'h00000000,
    32'h00000000,
    32'h00000000,
    32'h00000000,
    32'h00000000,
    32'h00000000,
    32'h00000000,
    32'h00000000,
    32'h00000000,
    32'h00000000,
    32'h00000000,
    32'h00000000,
    32'h00000000,
    32'h00000000,
    32'h00000000,
    32'h00000000,
    32'h00000000,
    32'h00000000,
    32'h00000000,
    32'h00000000,
    32'h00000000,
    32'h00000000,
    32'h00000000,
    32'h00000000,
    32'h00000000,
    32'h00000000,
    32'h00000000,
    32'h00000000,
    32'h00000000,
    32'h00000000,
    32'h00000000,
    32'h00000000,
    32'h00000000,
    32'h00000000,
    32'h00000000,
    32'h00000000,
    32'h00000000,
    32'h00000000,
    32'h00000000,
    32'h00000000,
    32'h00000000,
    32'h00000000,
    32'h00000000,
    32'h00000000,
    32'h00000000,
    32'h00000000,
    32'h00000000,
    32'h00000000,
    32'h00000000,
    32'h00000000,
    32'h00000000,
    32'h00000000,
    32'h00000000,
    32'h00000000,
    32'h00000000,
    32'h00000000,
    32'h00000000,
    32'h00000000,
    32'h00000000,
    32'h00000000,
    32'h00000000,
    32'h00000000,
    32'h00000000,
    32'h00000000,
    32'h00000000,
    32'h00000000,
    32'h00000000,
    32'h00000000,
    32'h00000000,
    32'h00000000,
    32'h00000000,
    32'h00000000,
    32'h00000000,
    32'h00000000,
    32'h00000000,
    32'h00000000,
    32'h00000000,
    32'h00000000,
    32'h00000000,
    32'h00000000,
    32'h00000000,
    32'h00000000,
    32'h00000000,
    32'h00000000,
    32'h00000000,
    32'h00000000,
    32'h00000000,
    32'h00000000,
    32'h00000000,
    32'h00000000,
    32'h00000000,
    32'h00000000,
    32'h00000000,
    32'h00000000,
    32'h00000023,
    32'h0000001e,
    32'h00000022,
    32'h00000021,
    32'h0000001e,
    32'h00000022,
    32'h00000023,
    32'h00000024,
    32'h00000022,
    32'h0000001f,
    32'h0000001e,
    32'h00000023,
    32'h0000001a,
    32'h00000020,
    32'h0000001f,
    32'h0000001e,
    32'h0000001f,
    32'h0000001d,
    32'h0000001b,
    32'h0000001e,
    32'h00000021,
    32'h00000022,
    32'h0000001e,
    32'h00000020,
    32'h0000001e,
    32'h0000001f,
    32'h00000022,
    32'h00000022,
    32'h00000021,
    32'h00000021,
    32'h0000001f,
    32'h0000001e,
    32'h00000022,
    32'h00000023,
    32'h00000020,
    32'h00000023,
    32'h00000021,
    32'h00000022,
    32'h0000001e,
    32'h0000001e,
    32'h00000023,
    32'h00000020,
    32'h00000022,
    32'h0000001f,
    32'h0000001d,
    32'h00000021,
    32'h00000020,
    32'h0000001d,
    32'h00000020,
    32'h0000001a,
    32'h0000001d,
    32'h00000021,
    32'h00000020,
    32'h00000021,
    32'h0000001b,
    32'h00000025,
    32'h00000022,
    32'h0000001f,
    32'h00000020,
    32'h00000023,
    32'h0000001d,
    32'h00000023,
    32'h0000001f,
    32'h0000001a,
    32'h00000029,
    32'h00000020,
    32'h00000024,
    32'h00000021,
    32'h0000001b,
    32'h00000021,
    32'h0000001c,
    32'h0000001e,
    32'h00000021,
    32'h00000020,
    32'h00000026,
    32'h00000020,
    32'h00000021,
    32'h0000001d,
    32'h0000001f,
    32'h00000023,
    32'h0000001e,
    32'h00000023,
    32'h00000021,
    32'h00000020,
    32'h00000020,
    32'h0000001e,
    32'h00000024,
    32'h00000020,
    32'h00000020,
    32'h0000001e,
    32'h00000020,
    32'h0000001d,
    32'h00000024,
    32'h0000001a,
    32'h00000021,
    32'h0000001e,
    32'h0000001b,
    32'h00000021,
    32'h00000021,
    32'h00000023,
    32'h0000001d,
    32'h0000001b,
    32'h00000021,
    32'h00000024,
    32'h00000022,
    32'h00000024,
    32'h0000001d,
    32'h00000021,
    32'h0000001f,
    32'h00000021,
    32'h00000020,
    32'h0000001a,
    32'h00000021,
    32'h00000022,
    32'h00000028,
    32'h0000001f,
    32'h00000020,
    32'h0000001d,
    32'h0000001d,
    32'h00000020,
    32'h0000001e,
    32'h0000001f,
    32'h00000023,
    32'h0000001e,
    32'h00000020,
    32'h00000020,
    32'h0000001e,
    32'h00000022,
    32'hffffffff,
    32'hffffffff,
    32'hffffffff,
    32'hffffffff,
    32'h5f225aad,
    32'h8529d7ba,
    32'h4b29da50,
    32'hd6a81042,
    32'he3146cf8,
    32'h7bafff90,
    32'he55c6434,
    32'h8fdc985a,
    32'hd9930729,
    32'hfeeddb82,
    32'h30c134ba,
    32'h19c31a7a,
    32'h58b0829b,
    32'hfd3d9415,
    32'hd7c71445,
    32'h30d2132e,
    32'h766d07c8,
    32'h372874f4,
    32'h490d33cc,
    32'hf97d3394,
    32'h090bb17b,
    32'h3370dd59,
    32'h4ea9accd,
    32'h73e4967d,
    32'h448d0879,
    32'h36e5ddc4,
    32'h2679ca08,
    32'h1f862614,
    32'h2144f12a,
    32'h80549cbb,
    32'h05325a13,
    32'hba5683aa,
    32'h38724090,
    32'h0c00fbe5,
    32'h0a2d8c23,
    32'h92298386,
    32'h9346065a,
    32'h3d98083d,
    32'hea81828e,
    32'he8d064ba,
    32'h00000000,
    32'h00000000,
    32'h00000000,
    32'h00000000,
    32'h00000000,
    32'h00000000,
    32'h00000000,
    32'h00000000,
    32'h00000000,
    32'h00000000
};

final-project/hw/model.sv
// Tiny binarized NN accelerator with XNOR-popcount + threshold + argmax.

// Synthesis-friendly ROM content provided via generated include.
`include "model.svh"

module tiny_bnn_accel #(
    parameter int unsigned DATA_WIDTH = 64,  // bits per incoming image payload
    parameter int unsigned TID_WIDTH  = 4
) (
    input logic clk,
    input logic rst_n,

    // Slave AXI-Stream input (image payload)
    input  logic [DATA_WIDTH-1:0] s_axis_tdata,
    input  logic                  s_axis_tvalid,
    output logic                  s_axis_tready,
    input  logic [ TID_WIDTH-1:0] s_axis_tid,

    // Master AXI-Stream output (classification result)
    output logic [          7:0] m_axis_tdata,
    output logic                 m_axis_tvalid,
    input  logic                 m_axis_tready,
    output logic [TID_WIDTH-1:0] m_axis_tid
);

  localparam int unsigned L1_IN = DATA_WIDTH;
  localparam int unsigned L1_OUT = 128;
  localparam int unsigned L2_IN = L1_OUT;
  localparam int unsigned L2_OUT = 10;

  localparam int unsigned L1_W_BITS = L1_IN * L1_OUT;
  localparam int unsigned L1_W_WORDS = (L1_W_BITS + 31) / 32;
  localparam int unsigned L1_B_WORDS = L1_OUT;
  localparam int unsigned L1_T_WORDS = L1_OUT;
  localparam int unsigned L1_S_WORDS = (L1_OUT + 31) / 32;
  localparam int unsigned L2_W_BITS = L2_IN * L2_OUT;
  localparam int unsigned L2_W_WORDS = (L2_W_BITS + 31) / 32;
  localparam int unsigned L2_B_WORDS = L2_OUT;

  localparam int unsigned MEM_DEPTH = L1_W_WORDS + L1_B_WORDS + L1_T_WORDS + L1_S_WORDS
                                      + L2_W_WORDS + L2_B_WORDS;

  localparam int unsigned L1_W_BASE = 0;
  localparam int unsigned L1_B_BASE = L1_W_BASE + L1_W_WORDS;
  localparam int unsigned L1_T_BASE = L1_B_BASE + L1_B_WORDS;
  localparam int unsigned L1_S_BASE = L1_T_BASE + L1_T_WORDS;
  localparam int unsigned L2_W_BASE = L1_S_BASE + L1_S_WORDS;
  localparam int unsigned L2_B_BASE = L2_W_BASE + L2_W_WORDS;

  logic [L1_OUT-1:0] hidden_bits_comb;
  logic [       7:0] pred_class_comb;

  logic [L1_OUT-1:0] hidden_bits_q;
  logic [       7:0] pred_class_q;

    assign s_axis_tready = ~m_axis_tvalid;

  // Compute hidden layer (XNOR-popcount >= threshold).
  always_comb begin
    hidden_bits_comb = '0;
    for (int o = 0; o < L1_OUT; o++) begin
      int match_count;
      int signed thr_val;
      match_count = 0;
      for (int i = 0; i < L1_IN; i++) begin
        int   idx;
        int   word_idx;
        int   bit_idx;
        logic weight_bit;
        idx        = i * L1_OUT + o;
        word_idx   = idx / 32;
        bit_idx    = idx % 32;
        weight_bit = MODEL_MEM[L1_W_BASE+word_idx][bit_idx];
        if (s_axis_tdata[i] == weight_bit) begin
          match_count++;
        end
      end
      thr_val = int'($signed(MODEL_MEM[L1_T_BASE+o][15:0]));
      begin
        int   sense_idx;
        int   sense_word;
        int   sense_bit;
        logic sense_pos;
        sense_idx  = o;
        sense_word = sense_idx / 32;
        sense_bit  = sense_idx % 32;
        sense_pos  = MODEL_MEM[L1_S_BASE+sense_word][sense_bit];
        if (sense_pos) begin
          hidden_bits_comb[o] = ($signed(match_count) >= thr_val);
        end else begin
          hidden_bits_comb[o] = ($signed(match_count) <= thr_val);
        end
      end
    end
  end

  // Compute output layer and argmax.
  always_comb begin
    int signed best_score;
    int best_class;
    best_score = -32'sd2000000000;
    best_class = 0;
    for (int c = 0; c < L2_OUT; c++) begin
      int match_count;
      int signed bias_q;
      int signed score;
      match_count = 0;
      for (int i = 0; i < L2_IN; i++) begin
        int   idx;
        int   word_idx;
        int   bit_idx;
        logic weight_bit;
        idx        = i * L2_OUT + c;
        word_idx   = idx / 32;
        bit_idx    = idx % 32;
        weight_bit = MODEL_MEM[L2_W_BASE+word_idx][bit_idx];
        if (hidden_bits_comb[i] == weight_bit) begin
          match_count++;
        end
      end
      bias_q = int'($signed(MODEL_MEM[L2_B_BASE+c][15:0]));
      score  = (match_count * 2 - L2_IN) + bias_q;
      if (score > best_score) begin
        best_score = score;
        best_class = c;
      end
    end
    pred_class_comb = best_class[7:0];
  end

  // Registers and handshake.
  always_ff @(posedge clk or negedge rst_n) begin
    if (!rst_n) begin
      hidden_bits_q <= '0;
      pred_class_q  <= '0;
      m_axis_tid    <= '0;
      m_axis_tdata  <= '0;
      m_axis_tvalid <= 1'b0;
    end else begin
      if (m_axis_tvalid && m_axis_tready) begin
        m_axis_tvalid <= 1'b0;
      end

      if (s_axis_tvalid && s_axis_tready) begin
        hidden_bits_q <= hidden_bits_comb;
        pred_class_q  <= pred_class_comb;
        m_axis_tid    <= s_axis_tid;
        m_axis_tdata  <= pred_class_comb;
        m_axis_tvalid <= 1'b1;
      end
    end
  end

endmodule

final-project/hw/dump.vcd
$version Generated by VerilatedVcd $end
$timescale 1ps $end
 $scope module $rootio $end
  $var wire 1 # clk $end
  $var wire 1 $ rst_n $end
  $var wire 64 % s_axis_tdata [63:0] $end
  $var wire 1 ' s_axis_tvalid $end
  $var wire 1 ( s_axis_tready $end
  $var wire 4 ) s_axis_tid [3:0] $end
  $var wire 8 * m_axis_tdata [7:0] $end
  $var wire 1 + m_axis_tvalid $end
  $var wire 1 , m_axis_tready $end
  $var wire 4 - m_axis_tid [3:0] $end
 $upscope $end
 $scope module tiny_bnn_accel $end
  $var wire 32 Z DATA_WIDTH [31:0] $end
  $var wire 32 [ TID_WIDTH [31:0] $end
  $var wire 1 . clk $end
  $var wire 1 / rst_n $end
  $var wire 64 0 s_axis_tdata [63:0] $end
  $var wire 1 2 s_axis_tvalid $end
  $var wire 1 3 s_axis_tready $end
  $var wire 4 4 s_axis_tid [3:0] $end
  $var wire 8 5 m_axis_tdata [7:0] $end
  $var wire 1 6 m_axis_tvalid $end
  $var wire 1 7 m_axis_tready $end
  $var wire 4 8 m_axis_tid [3:0] $end
  $var wire 32 Z L1_IN [31:0] $end
  $var wire 32 \ L1_OUT [31:0] $end
  $var wire 32 \ L2_IN [31:0] $end
  $var wire 32 ] L2_OUT [31:0] $end
  $var wire 32 ^ L1_W_BITS [31:0] $end
  $var wire 32 _ L1_W_WORDS [31:0] $end
  $var wire 32 \ L1_B_WORDS [31:0] $end
  $var wire 32 \ L1_T_WORDS [31:0] $end
  $var wire 32 [ L1_S_WORDS [31:0] $end
  $var wire 32 ` L2_W_BITS [31:0] $end
  $var wire 32 a L2_W_WORDS [31:0] $end
  $var wire 32 ] L2_B_WORDS [31:0] $end
  $var wire 32 b MEM_DEPTH [31:0] $end
  $var wire 32 c L1_W_BASE [31:0] $end
  $var wire 32 _ L1_B_BASE [31:0] $end
  $var wire 32 d L1_T_BASE [31:0] $end
  $var wire 32 e L1_S_BASE [31:0] $end
  $var wire 32 f L2_W_BASE [31:0] $end
  $var wire 32 g L2_B_BASE [31:0] $end
  $var wire 128 9 hidden_bits_comb [127:0] $end
  $var wire 8 = pred_class_comb [7:0] $end
  $var wire 128 > hidden_bits_q [127:0] $end
  $var wire 8 B pred_class_q [7:0] $end
  $scope module unnamedblk1 $end
   $var wire 32 C o [31:0] $end
   $scope module unnamedblk2 $end
    $var wire 32 D match_count [31:0] $end
    $var wire 32 E thr_val [31:0] $end
    $scope module unnamedblk3 $end
     $var wire 32 F i [31:0] $end
     $scope module unnamedblk4 $end
      $var wire 32 G idx [31:0] $end
      $var wire 32 H word_idx [31:0] $end
      $var wire 32 I bit_idx [31:0] $end
      $var wire 1 J weight_bit $end
     $upscope $end
    $upscope $end
    $scope module unnamedblk5 $end
     $var wire 32 K sense_idx [31:0] $end
     $var wire 32 L sense_word [31:0] $end
     $var wire 32 M sense_bit [31:0] $end
     $var wire 1 N sense_pos $end
    $upscope $end
   $upscope $end
  $upscope $end
  $scope module unnamedblk6 $end
   $var wire 32 O best_score [31:0] $end
   $var wire 32 P best_class [31:0] $end
   $scope module unnamedblk7 $end
    $var wire 32 Q c [31:0] $end
    $scope module unnamedblk8 $end
     $var wire 32 R match_count [31:0] $end
     $var wire 32 S bias_q [31:0] $end
     $var wire 32 T score [31:0] $end
     $scope module unnamedblk9 $end
      $var wire 32 U i [31:0] $end
      $scope module unnamedblk10 $end
       $var wire 32 V idx [31:0] $end
       $var wire 32 W word_idx [31:0] $end
       $var wire 32 X bit_idx [31:0] $end
       $var wire 1 Y weight_bit $end
      $upscope $end
     $upscope $end
    $upscope $end
   $upscope $end
  $upscope $end
 $upscope $end
$enddefinitions $end


#0
1#
0$
b0000000000000000000000000000000000000000000000000000000000000000 %
0'
1(
b0000 )
b00000000 *
0+
0,
b0000 -
1.
0/
b0000000000000000000000000000000000000000000000000000000000000000 0
02
13
b0000 4
b00000000 5
06
07
b0000 8
b11011111101101101111000000010011010001011011000101100011011011101101011010101111111110010111101111010001011111000001110001111011 9
b00000111 =
b00000000000000000000000000000000000000000000000000000000000000000000000000000000000000000000000000000000000000000000000000000000 >
b00000000 B
b00000000000000000000000010000000 C
b00000000000000000000000000100010 D
b00000000000000000000000000100010 E
b00000000000000000000000001000000 F
b00000000000000000001111111111111 G
b00000000000000000000000011111111 H
b00000000000000000000000000011111 I
0J
b00000000000000000000000001111111 K
b00000000000000000000000000000011 L
b00000000000000000000000000011111 M
1N
b00000000000000000000000000011110 O
b00000000000000000000000000000111 P
b00000000000000000000000000001010 Q
b00000000000000000000000000111101 R
b00000000000000000000000000000000 S
b11111111111111111111111111111010 T
b00000000000000000000000010000000 U
b00000000000000000000010011111111 V
b00000000000000000000000000100111 W
b00000000000000000000000000011111 X
1Y
b00000000000000000000000001000000 Z
b00000000000000000000000000000100 [
b00000000000000000000000010000000 \
b00000000000000000000000000001010 ]
b00000000000000000010000000000000 ^
b00000000000000000000000100000000 _
b00000000000000000000010100000000 `
b00000000000000000000000000101000 a
b00000000000000000000001000110110 b
b00000000000000000000000000000000 c
b00000000000000000000000110000000 d
b00000000000000000000001000000000 e
b00000000000000000000001000000100 f
b00000000000000000000001000101100 g
#5000
0#
0.
#10000
1#
1$
1.
1/
#15000
0#
0.
#20000
1#
1.
#25000
0#
0.
#30000
1#
1.
#35000
0#
0.
#40000
1#
1.
#45000
0#
0.
#50000
1#
1.
#50001
0$
0/
#55001
0#
0.
#60001
1#
1.
#65001
0#
0.
#70001
1#
1$
1.
1/
#75001
0#
0.
#80001
1#
b0111000001001000011111000000010000001100000011000001100000001000 %
1'
b0101 )
1,
1.
b0111000001001000011111000000010000001100000011000001100000001000 0
12
b0101 4
17
b00010000101011101111101110000111110000110110111011010110010011011111101011010111011111110000001111111111101111100101101010110101 9
b00000110 =
b00000000000000000000000000100000 D
b00000000000000000000000000110010 O
b00000000000000000000000000000110 P
b00000000000000000000000000110000 R
b11111111111111111111111111100000 T
#85001
0#
0.
#90001
1#
0'
0(
b00000110 *
1+
b0101 -
1.
02
03
b00000110 5
16
b0101 8
b00010000101011101111101110000111110000110110111011010110010011011111101011010111011111110000001111111111101111100101101010110101 >
b00000110 B
#95001
0#
0.
#100001
1#
1(
0+
1.
13
06
#105001
0#
0.
#110001
1#
1.
#110002
0$
b0000000000000000000000000000000000000000000000000000000000000000 %
b0000 )
b00000000 *
0,
b0000 -
0/
b0000000000000000000000000000000000000000000000000000000000000000 0
b0000 4
b00000000 5
07
b0000 8
b11011111101101101111000000010011010001011011000101100011011011101101011010101111111110010111101111010001011111000001110001111011 9
b00000111 =
b00000000000000000000000000000000000000000000000000000000000000000000000000000000000000000000000000000000000000000000000000000000 >
b00000000 B
b00000000000000000000000000100010 D
b00000000000000000000000000011110 O
b00000000000000000000000000000111 P
b00000000000000000000000000111101 R
b11111111111111111111111111111010 T
#115002
0#
0.
#120002
1#
1.
#125002
0#
0.
#130002
1#
1$
1.
1/
#135002
0#
0.
#140002
1#
b0000000000000000000000000000000000000000000000000001001000110100 %
1'
b0011 )
1.
b0000000000000000000000000000000000000000000000000001001000110100 0
12
b0011 4
b11011111111101101010010001000010001000111011010101100001111011101011111010101111111110010101100101000100010111000000110011101011 9
b00000000000000000000000000100011 D
b00000000000000000000000000011100 O
b00000000000000000000000000111010 R
b11111111111111111111111111110100 T
#145002
0#
0.
#150002
1#
0'
0(
b00000111 *
1+
b0011 -
1.
02
03
b00000111 5
16
b0011 8
b11011111111101101010010001000010001000111011010101100001111011101011111010101111111110010101100101000100010111000000110011101011 >
b00000111 B
#155002
0#
0.
#160002
1#
1.
#165002
0#
0.
#170002
1#
1.
#175002
0#
0.
#180002
1#
1.
#185002
0#
0.
#190002
1#
1,
1.
17
#195002
0#
0.
#200002
1#
1(
0+
1.
13
06
#200003
0$
b0000000000000000000000000000000000000000000000000000000000000000 %
b0000 )
b00000000 *
0,
b0000 -
0/
b0000000000000000000000000000000000000000000000000000000000000000 0
b0000 4
b00000000 5
07
b0000 8
b11011111101101101111000000010011010001011011000101100011011011101101011010101111111110010111101111010001011111000001110001111011 9
b00000000000000000000000000000000000000000000000000000000000000000000000000000000000000000000000000000000000000000000000000000000 >
b00000000 B
b00000000000000000000000000100010 D
b00000000000000000000000000011110 O
b00000000000000000000000000111101 R
b11111111111111111111111111111010 T
#205003
0#
0.
#210003
1#
1.
#215003
0#
0.
#220003
1#
1$
1.
1/
#225003
0#
0.
#230003
1#
b0111000001001000011111000000010000001100000011000001100000001000 %
1'
b0001 )
1,
1.
b0111000001001000011111000000010000001100000011000001100000001000 0
12
b0001 4
17
b00010000101011101111101110000111110000110110111011010110010011011111101011010111011111110000001111111111101111100101101010110101 9
b00000110 =
b00000000000000000000000000100000 D
b00000000000000000000000000110010 O
b00000000000000000000000000000110 P
b00000000000000000000000000110000 R
b11111111111111111111111111100000 T
#235003
0#
0.
#240003
1#
0'
0(
b00000110 *
1+
b0001 -
1.
02
03
b00000110 5
16
b0001 8
b00010000101011101111101110000111110000110110111011010110010011011111101011010111011111110000001111111111101111100101101010110101 >
b00000110 B
#245003
0#
0.
#250003
1#
1(
0+
1.
13
06
#255003
0#
0.
#260003
1#
b0001100000011000000111000001100000011000001110000001100000011000 %
1'
b1100 )
1.
b0001100000011000000111000001100000011000001110000001100000011000 0
12
b1100 4
b01110011101111010111001111110111011011111111000011101101011001010110000111111111101110101101110110000101011001011111101001100111 9
b00000001 =
b00000000000000000000000000101110 O
b00000000000000000000000000000001 P
b00000000000000000000000000110110 R
b11111111111111111111111111101100 T
#265003
0#
0.
#270003
1#
0'
0(
b00000001 *
1+
b1100 -
1.
02
03
b00000001 5
16
b1100 8
b01110011101111010111001111110111011011111111000011101101011001010110000111111111101110101101110110000101011001011111101001100111 >
b00000001 B
#275003
0#
0.
#280003
1#
1(
0+
1.
13
06
#285003
0#
0.
#290003
1#
b0011100000101100001011000011100000111000001110000011100000011000 %
1'
b1010 )
1.
b0011100000101100001011000011100000111000001110000011100000011000 0
12
b1010 4
b01001010011101010111101111110110111111111111010111111110001101010000001011110111100101101101011011011000001000011101001001111110 9
b00000000000000000000000000100001 D
b00000000000000000000000000100000 O
b00000000000000000000000000111011 R
b11111111111111111111111111110110 T
#295003
0#
0.
#300003
1#
0'
0(
1+
b1010 -
1.
02
03
16
b1010 8
b01001010011101010111101111110110111111111111010111111110001101010000001011110111100101101101011011011000001000011101001001111110 >
#305003
0#
0.
#310003
1#
1(
0+
1.
13
06
#315003
0#
0.
#320003
1#
b0001100000011000000110000001100000011000000110000001100000011000 %
1'
b0111 )
1.
b0001100000011000000110000001100000011000000110000001100000011000 0
12
b0111 4
b01111001100111011111001111010111011011111111010011101101011001110110100110111111101110101111110110001111011001001111101001100111 9
b00000000000000000000000000011110 D
b00000000000000000000000000101100 O
b00000000000000000000000000110111 R
b11111111111111111111111111101110 T
#325003
0#
0.
#330003
1#
0'
0(
1+
b0111 -
1.
02
03
16
b0111 8
b01111001100111011111001111010111011011111111010011101101011001110110100110111111101110101111110110001111011001001111101001100111 >
#335003
0#
0.
#340003
1#
1(
0+
1.
13
06
#345003
0#
0.
#350003
1#
b0011100000111000011000000110000000110000001100000011110000111000 %
1'
b0110 )
1.
b0011100000111000011000000110000000110000001100000011110000111000 0
12
b0110 4
b00111111010010111111001001111011111001101001010000101101000100100111011000001111110100011000011111011000010101001000100111101011 9
b00000011 =
b00000000000000000000000000100001 D
b00000000000000000000000001000000 O
b00000000000000000000000000000011 P
b00000000000000000000000001010011 R
b00000000000000000000000000100110 T
#355003
0#
0.
#360003
1#
0'
0(
b00000011 *
1+
b0110 -
1.
02
03
b00000011 5
16
b0110 8
b00111111010010111111001001111011111001101001010000101101000100100111011000001111110100011000011111011000010101001000100111101011 >
b00000011 B
#365003
0#
0.
#370003
1#
1(
0+
1.
13
06
#375003
0#
0.
#380003
1#
b0000100000001000000111000011100000110000001100000011110000011000 %
1'
b1101 )
1.
b0000100000001000000111000011100000110000001100000011110000011000 0
12
b1101 4
b10001011001000010111010000110010010010111111100001001111011001100100000010110010000110100101110110010001010001011001101001010111 9
b00000111 =
b00000000000000000000000000100110 D
b00000000000000000000000001001000 O
b00000000000000000000000000000111 P
b00000000000000000000000000111110 R
b11111111111111111111111111111100 T
#385003
0#
0.
#390003
1#
0'
0(
b00000111 *
1+
b1101 -
1.
02
03
b00000111 5
16
b1101 8
b10001011001000010111010000110010010010111111100001001111011001100100000010110010000110100101110110010001010001011001101001010111 >
b00000111 B
#395003
0#
0.
#400003
1#
1(
0+
1.
13
06
#405003
0#
0.
#410003
1#
b0111100001001100001111000000110000001100000011000001100000011000 %
1'
b0001 )
1.
b0111100001001100001111000000110000001100000011000001100000011000 0
12
b0001 4
b01010010111001101110111110000000111100110110111111010110010110011001101011110110111101100100101000101111101110100100101010111100 9
b00000110 =
b00000000000000000000000000100001 D
b00000000000000000000000000110000 O
b00000000000000000000000000000110 P
b00000000000000000000000000110001 R
b11111111111111111111111111100010 T
#415003
0#
0.
#420003
1#
0'
0(
b00000110 *
1+
b0001 -
1.
02
03
b00000110 5
16
b0001 8
b01010010111001101110111110000000111100110110111111010110010110011001101011110110111101100100101000101111101110100100101010111100 >
b00000110 B
#425003
0#
0.
#430003
1#
1(
0+
1.
13
06
#435003
0#
0.
